ppsspp_cwcheat_helpy/__init__.py
ppsspp_cwcheat_helpy/__main__.py
ppsspp_cwcheat_helpy/helpy.py
ppsspp_cwcheat_helpy-0.5.0.dist-info/licenses/LICENCE
ppsspp_cwcheat_helpy-0.5.0.dist-info/METADATA
ppsspp_cwcheat_helpy-0.5.0.dist-info/WHEEL
ppsspp_cwcheat_helpy-0.5.0.dist-info/entry_points.txt
ppsspp_cwcheat_helpy-0.5.0.dist-info/top_level.txt
ppsspp_cwcheat_helpy-0.5.0.dist-info/RECORD
