Metadata-Version: 2.4
Name: ppsspp-cwcheat-helpy
Version: 0.5.0
Summary: cwCheat address rewriter for PSP/PPSSPP memory patch lines
Author-email: Tim Abdiukov <TAbdiukov@gmail.com>
Project-URL: Homepage, https://github.com/TAbdiukov/ppsspp-cwcheat-helpy
Project-URL: Issues, https://github.com/TAbdiukov/ppsspp-cwcheat-helpy/issues
Keywords: ppsspp,psp,cwcheat,gaming
Classifier: Programming Language :: Python :: 3
Classifier: Operating System :: OS Independent
Classifier: Topic :: Games/Entertainment
Classifier: Topic :: Utilities
Classifier: Topic :: Software Development :: Build Tools
Classifier: Topic :: Software Development :: Disassemblers
Classifier: Topic :: Security
Classifier: Development Status :: 4 - Beta
Classifier: Environment :: Console
Classifier: Intended Audience :: Developers
Classifier: Intended Audience :: Science/Research
Requires-Python: >=3.8
License-File: LICENCE
Requires-Dist: pyperclip<2,>=1.9.0
Dynamic: license-file
